enaml_coverage_plugin/__init__.py
enaml_coverage_plugin/parser.py
enaml_coverage_plugin/plugin.py
enaml_coverage_plugin/reporter.py
enaml_coverage_plugin/version.py
enaml_coverage_plugin-0.2.0.dist-info/AUTHORS
enaml_coverage_plugin-0.2.0.dist-info/LICENSE
enaml_coverage_plugin-0.2.0.dist-info/METADATA
enaml_coverage_plugin-0.2.0.dist-info/WHEEL
enaml_coverage_plugin-0.2.0.dist-info/top_level.txt
enaml_coverage_plugin-0.2.0.dist-info/RECORD
