Metadata-Version: 2.1
Name: enaml-coverage-plugin
Version: 0.2.0
Summary: Coverage plugin for enaml
Author-email: "Matthieu C. Dartiailh" <m.dartiailh@gmail.com>
License: Copyright (c) 2016-2021, Enaml coverage plugin authors
Project-URL: homepage, https://github.com/MatthieuDartiailh/enaml_coverage_plugin
Project-URL: repository, https://github.com/MatthieuDartiailh/enaml_coverage_plugin
Project-URL: changelog, https://github.com/MatthieuDartiailh/enaml_coverage_plugin/blob/main/releasenotes.rst
Classifier: Development Status :: 3 - Alpha
Classifier: License :: OSI Approved :: BSD License
Classifier: Natural Language :: English
Classifier: Operating System :: OS Independent
Classifier: Programming Language :: Python
Classifier: Programming Language :: Python :: 3
Classifier: Programming Language :: Python :: 3.8
Classifier: Programming Language :: Python :: 3.9
Classifier: Programming Language :: Python :: 3.10
Classifier: Programming Language :: Python :: 3.11
Classifier: Programming Language :: Python :: Implementation :: CPython
Requires-Python: >=3.8
License-File: LICENSE
License-File: AUTHORS
Requires-Dist: coverage
Requires-Dist: enaml (>=0.16)
